bowshockpy/__init__.py
bowshockpy/cubemass.py
bowshockpy/cubeproc.py
bowshockpy/genbow.py
bowshockpy/modelproj.py
bowshockpy/models.py
bowshockpy/moments.py
bowshockpy/plots.py
bowshockpy/radtrans.py
bowshockpy/rotlinearmol.py
bowshockpy/utils.py
bowshockpy/version.py
bowshockpy/inputfiles/__init__.py
bowshockpy/inputfiles/example1.py
bowshockpy/inputfiles/example2.py
bowshockpy/inputfiles/example3.py
bowshockpy/inputfiles/example4.py
bowshockpy/inputfiles/example5.py
bowshockpy-1.0.0.dist-info/licenses/LICENSE
docs/source/conf.py
examples/example1.py
examples/example2.py
examples/example3.py
examples/example4.py
examples/example5.py
tests/__init__.py
tests/test_cubes.py
tests/test_examples.py
tests/test_models.py
tests/test_radtrans.py
bowshockpy-1.0.0.dist-info/METADATA
bowshockpy-1.0.0.dist-info/WHEEL
bowshockpy-1.0.0.dist-info/entry_points.txt
bowshockpy-1.0.0.dist-info/top_level.txt
bowshockpy-1.0.0.dist-info/RECORD
