Metadata-Version: 2.4
Name: bowshockpy
Version: 1.0.0
Summary: A Python package for generating spectral channel maps of a jet-driven bowshock model
Author-email: Guillermo Blazquez-Calero <gblazquez@iaa.es>
Maintainer-email: Guillermo Blazquez-Calero <gblazquez@iaa.es>
License-Expression: MIT
Project-URL: Homepage, https://github.com/gblazquez/bowshockpy
Project-URL: Documentation, https://bowshockpy.readthedocs.io/en/latest/
Project-URL: Repository, https://github.com/gblazquez/bowshockpy
Requires-Python: >=3.9
License-File: LICENSE
Requires-Dist: numpy
Requires-Dist: matplotlib
Requires-Dist: scipy
Requires-Dist: astropy
Requires-Dist: photutils
Provides-Extra: dev
Requires-Dist: pytest; extra == "dev"
Requires-Dist: pytest-cov; extra == "dev"
Provides-Extra: doc
Requires-Dist: sphinx; extra == "doc"
Requires-Dist: sphinx-book-theme; extra == "doc"
Dynamic: license-file
